COPYING
MANIFEST.in
README.rst
setup.py
squery_pg/__init__.py
squery_pg/migrations.py
squery_pg/pool.py
squery_pg/pytest_fixtures.py
squery_pg/squery_pg.py
squery_pg/testing.py
squery_pg/utils.py
squery_pg.egg-info/PKG-INFO
squery_pg.egg-info/SOURCES.txt
squery_pg.egg-info/dependency_links.txt
squery_pg.egg-info/requires.txt
squery_pg.egg-info/top_level.txt