Metadata-Version: 1.1
Name: squery-pg
Version: 1.3
Summary: UNKNOWN
Home-page: https://github.com/Outernet-Project/squery-pg
Author: Outernet Inc
Author-email: apps@outernet.is
License: GPLv3
Platform: UNKNOWN
Classifier: Development Status :: 3 - Alpha
Classifier: License :: OSI Approved :: GNU General Public License v3 (GPLv3)
Classifier: Programming Language :: Python :: 2.7
Classifier: Programming Language :: Python :: 3.4
Classifier: Topic :: Software Development :: Libraries
